{
    "os": "Linux-4.18.0-193.28.1.el8_2.x86_64-x86_64-with-glibc2.28",
    "python": "3.9.6",
    "heartbeatAt": "2023-11-08T12:10:43.802251",
    "startedAt": "2023-11-08T12:10:42.969708",
    "docker": null,
    "cuda": null,
    "args": [],
    "state": "running",
    "program": "/ocean/projects/asc170022p/lisun/xinliu/fewshot/Renet-MLTI/gchtmp.py",
    "codePathLocal": "gchtmp.py",
    "codePath": "gchtmp.py",
    "git": {
        "remote": "https://github.com/ygritte723/Renet-pytorch.git",
        "commit": "3797c38039066c52db9307eb580a809e7afd549e"
    },
    "email": null,
    "root": "/ocean/projects/asc170022p/lisun/xinliu/fewshot/Renet-MLTI",
    "host": "dv001.ib.bridges2.psc.edu",
    "username": "lisun",
    "executable": "/ocean/projects/asc170022p/lisun/miniconda3/envs/fewshot/bin/python",
    "cpu_count": 32,
    "cpu_count_logical": 32,
    "cpu_freq": {
        "current": 1873.1816875000002,
        "min": 1500.0,
        "max": 3000.0
    },
    "cpu_freq_per_core": [
        {
            "current": 2141.03,
            "min": 1500.0,
            "max": 3000.0
        },
        {
            "current": 1723.632,
            "min": 1500.0,
            "max": 3000.0
        },
        {
            "current": 2001.254,
            "min": 1500.0,
            "max": 3000.0
        },
        {
            "current": 1702.047,
            "min": 1500.0,
            "max": 3000.0
        },
        {
            "current": 2001.337,
            "min": 1500.0,
            "max": 3000.0
        },
        {
            "current": 1643.563,
            "min": 1500.0,
            "max": 3000.0
        },
        {
            "current": 1498.568,
            "min": 1500.0,
            "max": 3000.0
        },
        {
            "current": 1652.703,
            "min": 1500.0,
            "max": 3000.0
        },
        {
            "current": 1508.373,
            "min": 1500.0,
            "max": 3000.0
        },
        {
            "current": 1787.94,
            "min": 1500.0,
            "max": 3000.0
        },
        {
            "current": 1761.774,
            "min": 1500.0,
            "max": 3000.0
        },
        {
            "current": 1525.198,
            "min": 1500.0,
            "max": 3000.0
        },
        {
            "current": 1661.859,
            "min": 1500.0,
            "max": 3000.0
        },
        {
            "current": 2292.784,
            "min": 1500.0,
            "max": 3000.0
        },
        {
            "current": 2152.568,
            "min": 1500.0,
            "max": 3000.0
        },
        {
            "current": 2125.342,
            "min": 1500.0,
            "max": 3000.0
        },
        {
            "current": 1799.544,
            "min": 1500.0,
            "max": 3000.0
        },
        {
            "current": 1797.872,
            "min": 1500.0,
            "max": 3000.0
        },
        {
            "current": 1646.906,
            "min": 1500.0,
            "max": 3000.0
        },
        {
            "current": 1700.177,
            "min": 1500.0,
            "max": 3000.0
        },
        {
            "current": 1797.533,
            "min": 1500.0,
            "max": 3000.0
        },
        {
            "current": 1798.047,
            "min": 1500.0,
            "max": 3000.0
        },
        {
            "current": 1536.075,
            "min": 1500.0,
            "max": 3000.0
        },
        {
            "current": 1799.165,
            "min": 1500.0,
            "max": 3000.0
        },
        {
            "current": 1629.086,
            "min": 1500.0,
            "max": 3000.0
        },
        {
            "current": 1641.133,
            "min": 1500.0,
            "max": 3000.0
        },
        {
            "current": 1497.809,
            "min": 1500.0,
            "max": 3000.0
        },
        {
            "current": 1785.049,
            "min": 1500.0,
            "max": 3000.0
        },
        {
            "current": 1800.445,
            "min": 1500.0,
            "max": 3000.0
        },
        {
            "current": 1798.198,
            "min": 1500.0,
            "max": 3000.0
        },
        {
            "current": 1797.591,
            "min": 1500.0,
            "max": 3000.0
        },
        {
            "current": 1798.242,
            "min": 1500.0,
            "max": 3000.0
        }
    ],
    "disk": {
        "/": {
            "total": 294.29180908203125,
            "used": 16.735816955566406
        }
    },
    "gpu": "Quadro RTX 5000",
    "gpu_count": 1,
    "gpu_devices": [
        {
            "name": "Quadro RTX 5000",
            "memory_total": 17179869184
        }
    ],
    "memory": {
        "total": 251.75424194335938
    }
}
